ag_grid/__init__.py
ag_grid/admin.py
ag_grid/api.py
ag_grid/consumers.py
ag_grid/grid.py
ag_grid/log.py
ag_grid/models.py
ag_grid/permissions.py
ag_grid/registry.py
ag_grid/resource.py
ag_grid/routing.py
ag_grid/serializers.py
ag_grid/urls.py
ag_grid/utils.py
ag_grid/contrib/notification/__init__.py
ag_grid/contrib/notification/admin.py
ag_grid/contrib/notification/api.py
ag_grid/contrib/notification/apps.py
ag_grid/contrib/notification/consumers.py
ag_grid/contrib/notification/models.py
ag_grid/contrib/notification/signals.py
ag_grid/contrib/notification/urls.py
ag_grid/contrib/notification/utils.py
ag_grid/contrib/notification/templates/notification/notification_center.html
ag_grid/contrib/notification/templates/notification/toast.html
ag_grid/contrib/notification/templates/notification/css/notification.css
ag_grid/contrib/notification/templates/notification/js/notification.js
ag_grid_django_kasie-0.0.7.83.dist-info/METADATA
ag_grid_django_kasie-0.0.7.83.dist-info/WHEEL
ag_grid_django_kasie-0.0.7.83.dist-info/top_level.txt
ag_grid_django_kasie-0.0.7.83.dist-info/RECORD
