Metadata-Version: 2.4
Name: ag-grid-django-kasie
Version: 0.0.7.83
Summary: A Django app that integrates AG Grid for advanced data grid functionalities
Home-page: https://github.com/kyong-dev/ag-grid-django
Author: kasie
Author-email: cod.kms@gmail.com
Keywords: ag-grid,django,ag-grid django,aggrid,aggrid django
Classifier: Programming Language :: Python :: 3.10
Classifier: Programming Language :: Python :: 3.11
Classifier: Programming Language :: Python :: 3.12
Requires-Python: >=3.10
Requires-Dist: openpyxl>=3.1.5
Dynamic: author
Dynamic: author-email
Dynamic: classifier
Dynamic: home-page
Dynamic: keywords
Dynamic: requires-dist
Dynamic: requires-python
Dynamic: summary
